dynadojo/LICENSE
dynadojo/__init__.py
dynadojo/abstractions.py
dynadojo/challenges.py
dynadojo/baselines/__init__.py
dynadojo/baselines/cnn.py
dynadojo/baselines/dmd.py
dynadojo/baselines/dnn.py
dynadojo/baselines/lpr.py
dynadojo/baselines/lr.py
dynadojo/baselines/sindy.py
dynadojo/systems/__init__.py
dynadojo/systems/ca.py
dynadojo/systems/ctln.py
dynadojo/systems/heat.py
dynadojo/systems/kuramoto.py
dynadojo/systems/lds.py
dynadojo/systems/lorenz.py
dynadojo/systems/santi.py
dynadojo/systems/snn.py
dynadojo/systems/utils.py
dynadojo/systems/epidemic/__init__.py
dynadojo/systems/epidemic/seis.py
dynadojo/systems/epidemic/sir.py
dynadojo/systems/epidemic/sis.py
dynadojo/systems/fbsnn_pde/__init__.py
dynadojo/systems/fbsnn_pde/bsb.py
dynadojo/systems/fbsnn_pde/hjb.py
dynadojo/systems/lv/__init__.py
dynadojo/systems/lv/competitive.py
dynadojo/systems/lv/prey_predator.py
dynadojo/systems/opinion/__init__.py
dynadojo/systems/opinion/arwhk.py
dynadojo/systems/opinion/deffuant.py
dynadojo/systems/opinion/hk.py
dynadojo/systems/opinion/media_bias.py
dynadojo/systems/opinion/whk.py
dynadojo/testing/__init__.py
dynadojo/testing/systems.py
dynadojo/utils/__init__.py
dynadojo/utils/ca.py
dynadojo/utils/fbsnn_pde.py
dynadojo/utils/heat.py
dynadojo/utils/kuramoto.py
dynadojo/utils/lds.py
dynadojo/utils/lv.py
dynadojo/utils/opinion.py
dynadojo/utils/plotting.py
dynadojo-0.2.6.dist-info/LICENSE
dynadojo-0.2.6.dist-info/WHEEL
dynadojo-0.2.6.dist-info/METADATA
dynadojo-0.2.6.dist-info/RECORD
