Metadata-Version: 2.1
Name: dynadojo
Version: 0.2.6
Summary: An extensible platform for benchmarking sample efficiency in dynamical system identification
Author: Logan Mondal Bhamidipaty <loganmb@stanford.edu>, Tommy Anthony Bruzzese <tbru@stanford.edu>, Max Kanwal <kanwal@stanford.edu>, Rami Ratl Mrad <ramiratlmrad@berkeley.edu>
Classifier: License :: OSI Approved :: MIT License
Requires-Dist: networkx
Requires-Dist: tqdm>=4.65.0
Requires-Dist: numpy>=1.23.5
Requires-Dist: torch>=2.0.1
Requires-Dist: torchdiffeq>=0.2.3
Requires-Dist: joblib>=1.2.0
Requires-Dist: keras>=2.12.0
Requires-Dist: tensorflow
Requires-Dist: seaborn>=0.12.2
Requires-Dist: scipy>=1.10.1
Requires-Dist: scikit-learn>=1.2.2
Requires-Dist: cellpylib
Requires-Dist: matplotlib
Requires-Dist: pandas
Requires-Dist: ndlib
Requires-Dist: pydmd
Requires-Dist: pysindy
Requires-Dist: setuptools
Requires-Dist: rebound ; extra == "nbody"
Project-URL: Home, https://github.com/FlyingWorkshop/dynadojo/
Provides-Extra: nbody
